Metadata-Version: 2.4
Name: gorunn
Version: 0.1.10
Summary: CLI tool for managing local environments
Author-email: Goran Parapid <goran@parapid.com>
License: Apache Software License
Project-URL: Homepage, https://github.com/parapidcom/gorunn
Project-URL: Repository, https://github.com/parapidcom/gorunn
Project-URL: Issues, https://github.com/parapidcom/gorunn/issues
Keywords: cli,docker,development,environment
Classifier: Programming Language :: Python :: 3
Classifier: License :: OSI Approved :: Apache Software License
Classifier: Operating System :: MacOS
Requires-Python: >=3.9
License-File: LICENSE
Requires-Dist: click==8.1.7
Requires-Dist: gitdb==4.0.11
Requires-Dist: GitPython==3.1.43
Requires-Dist: Jinja2==3.1.4
Requires-Dist: MarkupSafe==2.1.5
Requires-Dist: PyYAML==6.0.1
Requires-Dist: smmap==5.0.1
Requires-Dist: requests==2.32.2
Requires-Dist: boto3==1.34.101
Requires-Dist: packaging==24.0
Requires-Dist: python-dotenv==1.0.1
Requires-Dist: inquirer==3.4.0
Requires-Dist: psutil==6.1.0
Requires-Dist: cryptography==43.0.3
Dynamic: license-file
